pykkar.py
pykkar-1.5.dist-info/METADATA
pykkar-1.5.dist-info/WHEEL
pykkar-1.5.dist-info/top_level.txt
pykkar-1.5.dist-info/RECORD
