Metadata-Version: 2.1
Name: pykkar
Version: 1.5
Summary: Virtual robot library for teaching programming
Home-page: https://bitbucket.org/plas/pykkar
Author: Aivar Annamaa
Author-email: UNKNOWN
License: MIT
Keywords: robot pykkar education karel
Platform: UNKNOWN
Classifier: Development Status :: 5 - Production/Stable
Classifier: Intended Audience :: Education
Classifier: License :: Freeware
Classifier: License :: OSI Approved :: MIT License
Classifier: Natural Language :: English
Classifier: Programming Language :: Python
Classifier: Programming Language :: Python :: 2
Classifier: Programming Language :: Python :: 3
Classifier: Topic :: Education
